cli/__init__.py
cli/ezo_cli.py
core/__init__.py
core/helpers.py
core/lib.py
core/utils.py
core/views.py
ezo-0.1.2.data/scripts/start.py
ezo-0.1.2.dist-info/METADATA
ezo-0.1.2.dist-info/RECORD
ezo-0.1.2.dist-info/WHEEL
ezo-0.1.2.dist-info/entry_points.txt
ezo-0.1.2.dist-info/top_level.txt
