Metadata-Version: 2.1
Name: ezo
Version: 0.1.2
Summary: ezo - easy Ethereum oracles
Home-page: https://github.com/robinagist/ezo
Author: Robin A. Gist
Author-email: robinagist@gmail.com
License: UNKNOWN
Platform: UNKNOWN
Classifier: Programming Language :: Python :: 3.6
Classifier: License :: OSI Approved :: MIT License
Classifier: Operating System :: OS Independent
Requires-Python: >=3.6
Requires-Dist: cement
Requires-Dist: configobj
Requires-Dist: cytoolz
Requires-Dist: eth-abi
Requires-Dist: eth-account
Requires-Dist: eth-hash
Requires-Dist: eth-keyfile
Requires-Dist: eth-keys
Requires-Dist: eth-rlp
Requires-Dist: eth-utils
Requires-Dist: hexbytes
Requires-Dist: idna
Requires-Dist: inflection
Requires-Dist: lru-dict
Requires-Dist: plyvel
Requires-Dist: py-solc
Requires-Dist: pycryptodome
Requires-Dist: requests
Requires-Dist: requests-toolbelt
Requires-Dist: web3
Requires-Dist: toolz
Requires-Dist: tqdm
Requires-Dist: urllib3
Requires-Dist: websockets
Requires-Dist: xkcdpass
Requires-Dist: xxhash
